unification/__init__.py
unification/core.py
unification/dispatch.py
unification/more.py
unification/util.py
unification/variable.py
unification-0.3.1.dist-info/licenses/LICENSE.txt
unification-0.3.1.dist-info/METADATA
unification-0.3.1.dist-info/WHEEL
unification-0.3.1.dist-info/top_level.txt
unification-0.3.1.dist-info/RECORD
